[{"textRange":[171,11],"text":"Introducing","timeOffset":500000},{"textRange":[183,3],"text":"the","timeOffset":7875000},{"textRange":[187,8],"text":"sentence","timeOffset":9000000},{"textRange":[196,7],"text":"element","timeOffset":13625000},{"textRange":[203,1],"text":".","timeOffset":19750000},{"textRange":[232,4],"text":"Used","timeOffset":28375000},{"textRange":[237,2],"text":"to","timeOffset":31500000},{"textRange":[240,4],"text":"mark","timeOffset":32375000},{"textRange":[245,10],"text":"individual","timeOffset":35500000},{"textRange":[256,9],"text":"sentences","timeOffset":41375000},{"textRange":[265,1],"text":".","timeOffset":50500000},{"textRange":[332,7],"text":"Another","timeOffset":59125000},{"textRange":[340,6],"text":"simple","timeOffset":63375000},{"textRange":[347,9],"text":"paragraph","timeOffset":66875000},{"textRange":[356,1],"text":".","timeOffset":74625000},{"textRange":[378,8],"text":"Sentence","timeOffset":83250000},{"textRange":[387,9],"text":"structure","timeOffset":88375000},{"textRange":[397,2],"text":"in","timeOffset":92500000},{"textRange":[400,4],"text":"this","timeOffset":93500000},{"textRange":[405,9],"text":"paragraph","timeOffset":95250000},{"textRange":[415,2],"text":"is","timeOffset":102375000},{"textRange":[418,3],"text":"not","timeOffset":103625000},{"textRange":[422,10],"text":"explicitly","timeOffset":105875000},{"textRange":[433,6],"text":"marked","timeOffset":112125000},{"textRange":[439,1],"text":".","timeOffset":117375000}]
